sqlalchemy_clickhouse_timezone
