Metadata-Version: 1.1
Name: sqlalchemy-clickhouse-timezone
Version: 0.1.3
Summary: ClickHouse SQLAlchemy Dialect with timezone support
Home-page: https://github.com/ufully/sqlalchemy-clickhouse-timezone
Author: 21499836@qq.com
Author-email: 21499836@qq.com
License: Apache License, Version 2.0
Download-URL: https://github.com/ufully/sqlalchemy-clickhouse-timezone/releases/tag/v0.1.0
Keywords: db database cloud analytics clickhouse with tiemzone support
Platform: UNKNOWN
Classifier: Development Status :: 5 - Production/Stable
Classifier: Environment :: Console
Classifier: Environment :: Other Environment
Classifier: Intended Audience :: Developers
Classifier: Intended Audience :: Education
Classifier: Intended Audience :: Information Technology
Classifier: Intended Audience :: System Administrators
Classifier: License :: OSI Approved :: Apache Software License
Classifier: Operating System :: OS Independent
Classifier: Programming Language :: SQL
Classifier: Programming Language :: Python :: 2.7
Classifier: Programming Language :: Python :: 3.4
Classifier: Programming Language :: Python :: 3.5
Classifier: Topic :: Database
Classifier: Topic :: Software Development
Classifier: Topic :: Software Development :: Libraries
Classifier: Topic :: Software Development :: Libraries :: Application Frameworks
Classifier: Topic :: Software Development :: Libraries :: Python Modules
